blowtorch/__init__.py
blowtorch/bound_functions.py
blowtorch/config.py
blowtorch/loggers.py
blowtorch/run.py
blowtorch/setup.py
blowtorch/utils.py
blowtorch/backends/__init__.py
blowtorch/backends/apply_func.py
blowtorch/backends/base_backend.py
blowtorch/backends/cpu_backend.py
blowtorch/backends/gpu_backend.py
blowtorch-0.5.4.dist-info/LICENSE
blowtorch-0.5.4.dist-info/METADATA
blowtorch-0.5.4.dist-info/WHEEL
blowtorch-0.5.4.dist-info/top_level.txt
blowtorch-0.5.4.dist-info/RECORD
