Metadata-Version: 2.1
Name: blowtorch
Version: 0.5.4
Summary: Intuitive training framework for PyTorch
Home-page: https://github.com/alebeck/blowtorch
Author: Alexander Becker
License: UNKNOWN
Platform: UNKNOWN
Classifier: Programming Language :: Python :: 3
Classifier: License :: OSI Approved :: MIT License
Classifier: Operating System :: OS Independent
Requires-Python: >=3.8
License-File: LICENSE
Requires-Dist: wheel
Requires-Dist: colorama (==0.4)
Requires-Dist: ruamel.yaml
Requires-Dist: halo (==0.0.31)
Requires-Dist: coolname (==1.1)
Requires-Dist: tqdm (==4.30)
